highdicom/__init__.py
highdicom/_iods.py
highdicom/_module_utils.py
highdicom/_modules.py
highdicom/base.py
highdicom/base_content.py
highdicom/coding_schemes.py
highdicom/color.py
highdicom/content.py
highdicom/enum.py
highdicom/frame.py
highdicom/image.py
highdicom/io.py
highdicom/pixels.py
highdicom/py.typed
highdicom/spatial.py
highdicom/uid.py
highdicom/utils.py
highdicom/valuerep.py
highdicom/version.py
highdicom/volume.py
highdicom/_icc_profiles/sRGB_v4_ICC_preference.icc
highdicom/ann/__init__.py
highdicom/ann/content.py
highdicom/ann/enum.py
highdicom/ann/sop.py
highdicom/ko/__init__.py
highdicom/ko/content.py
highdicom/ko/sop.py
highdicom/legacy/__init__.py
highdicom/legacy/sop.py
highdicom/pm/__init__.py
highdicom/pm/content.py
highdicom/pm/enum.py
highdicom/pm/sop.py
highdicom/pr/__init__.py
highdicom/pr/content.py
highdicom/pr/enum.py
highdicom/pr/sop.py
highdicom/sc/__init__.py
highdicom/sc/enum.py
highdicom/sc/sop.py
highdicom/seg/__init__.py
highdicom/seg/content.py
highdicom/seg/enum.py
highdicom/seg/pyramid.py
highdicom/seg/sop.py
highdicom/seg/utils.py
highdicom/sr/__init__.py
highdicom/sr/coding.py
highdicom/sr/content.py
highdicom/sr/enum.py
highdicom/sr/sop.py
highdicom/sr/templates.py
highdicom/sr/utils.py
highdicom/sr/value_types.py
highdicom-0.26.1.dist-info/licenses/LICENSE
highdicom-0.26.1.dist-info/METADATA
highdicom-0.26.1.dist-info/WHEEL
highdicom-0.26.1.dist-info/top_level.txt
highdicom-0.26.1.dist-info/RECORD
