Metadata-Version: 2.4
Name: highdicom
Version: 0.26.1
Summary: High-level DICOM abstractions.
Author: Markus D. Herrmann, Christopher P. Bridge
Maintainer: Markus D. Herrmann, Christopher P. Bridge
License: LICENSE
Project-URL: homepage, https://github.com/imagingdatacommons/highdicom
Project-URL: documentation, https://highdicom.readthedocs.io/
Project-URL: repository, https://github.com/ImagingDataCommons/highdicom.git
Classifier: Development Status :: 4 - Beta
Classifier: Intended Audience :: Science/Research
Classifier: License :: OSI Approved :: MIT License
Classifier: Operating System :: MacOS
Classifier: Operating System :: Microsoft :: Windows
Classifier: Operating System :: POSIX :: Linux
Classifier: Programming Language :: Python :: 3
Classifier: Programming Language :: Python :: 3.10
Classifier: Programming Language :: Python :: 3.11
Classifier: Programming Language :: Python :: 3.12
Classifier: Programming Language :: Python :: 3.13
Classifier: Topic :: Multimedia :: Graphics
Classifier: Topic :: Scientific/Engineering :: Information Analysis
Requires-Python: >=3.10
License-File: LICENSE
Requires-Dist: numpy>=1.19
Requires-Dist: pillow>=8.3
Requires-Dist: pydicom>=3.0.1
Requires-Dist: pyjpegls>=1.0.0
Requires-Dist: typing-extensions>=4.0.0
Provides-Extra: libjpeg
Requires-Dist: pylibjpeg-libjpeg>=2.1; extra == "libjpeg"
Requires-Dist: pylibjpeg-openjpeg>=2.0.0; extra == "libjpeg"
Requires-Dist: pylibjpeg>=2.0; extra == "libjpeg"
Provides-Extra: test
Requires-Dist: mypy==1.15.0; extra == "test"
Requires-Dist: pytest==8.3.5; extra == "test"
Requires-Dist: pytest-cov==6.1.1; extra == "test"
Requires-Dist: pytest-flake8==1.3.0; extra == "test"
Provides-Extra: docs
Requires-Dist: sphinx-autodoc-typehints==1.17.0; extra == "docs"
Requires-Dist: sphinx-pyreverse==0.0.17; extra == "docs"
Requires-Dist: sphinx-rtd-theme==1.0.0; extra == "docs"
Requires-Dist: sphinxcontrib-autoprogram==0.1.7; extra == "docs"
Requires-Dist: sphinxcontrib-websupport==1.2.4; extra == "docs"
Dynamic: license-file
